scitrera_rt_data/__init__.py
scitrera_rt_data/dt.py
scitrera_rt_data/kv/__init__.py
scitrera_rt_data/kv/_base.py
scitrera_rt_data/kv/in_memory.py
scitrera_rt_data/kv/redis_raw_ttl.py
scitrera_rt_data/kv/redis_ttl/__init__.py
scitrera_rt_data/kv/redis_ttl/json.py
scitrera_rt_data/kv/redis_ttl/msgpack.py
scitrera_rt_data/kv/redis_ttl/pickle.py
scitrera_rt_data/locks/__init__.py
scitrera_rt_data/locks/_base.py
scitrera_rt_data/locks/in_process.py
scitrera_rt_data/locks/redis_lock_async2.py
scitrera_rt_data/q/__init__.py
scitrera_rt_data/q/async_redis_q.py
scitrera_rt_data/redis_/__init__.py
scitrera_rt_data/remote_rest/__init__.py
scitrera_rt_data/remote_rest/date_chunking.py
scitrera_rt_data/rmq/__init__.py
scitrera_rt_data/serialization/__init__.py
scitrera_rt_data/serialization/_common.py
scitrera_rt_data/serialization/json.py
scitrera_rt_data/serialization/msgpack.py
scitrera_rt_data/sql/__init__.py
scitrera_rt_data/sql/asyncpg_.py
scitrera_rt_data/sql/sqlalchemy_.py
scitrera_rt_data/tkvt/__init__.py
scitrera_rt_data/tkvt/_base.py
scitrera_rt_data/tkvt/asyncio/__init__.py
scitrera_rt_data/tkvt/asyncio/in_process.py
scitrera_rt_data/tkvt/asyncio/kafka.py
scitrera_rt_data/tkvt/asyncio/redis_streams.py
scitrera_rt_data/tkvt/asyncio/rmq_streams.py
scitrera_rt_data/tkvt/sync/__init__.py
scitrera_rt_data/tkvt/sync/in_process.py
scitrera_rt_data/tkvt/sync/kafka.py
scitrera_rt_data/tkvt/sync/logging.py
scitrera_rt_data/tkvt/sync/redis_streams.py
scitrera_rt_data/tkvt/sync/rmq_streams.py
scitrera_rt_data/tls/__init__.py
scitrera_rt_data-0.0.4.dist-info/licenses/LICENSE
scitrera_rt_data-0.0.4.dist-info/METADATA
scitrera_rt_data-0.0.4.dist-info/WHEEL
scitrera_rt_data-0.0.4.dist-info/top_level.txt
scitrera_rt_data-0.0.4.dist-info/RECORD
