Metadata-Version: 2.4
Name: scitrera-rt-data
Version: 0.0.4
Summary: Utilities for real-time data applications
Author: Scitrera LLC
License: BSD-3-Clause
Project-URL: Homepage, https://github.com/scitrera/scitrera-rt-data-python
Project-URL: Issues, https://github.com/scitrera/scitrera-rt-data-python/issues
Classifier: Programming Language :: Python :: 3
Classifier: License :: OSI Approved :: BSD License
Classifier: Operating System :: OS Independent
Requires-Python: >=3.9
License-File: LICENSE
Requires-Dist: pandas
Requires-Dist: pytz
Requires-Dist: python-dateutil
Requires-Dist: scitrera-app-framework
Requires-Dist: tenacity
Provides-Extra: redis
Requires-Dist: redis[hiredis]>=4.0.0; extra == "redis"
Requires-Dist: msgpack>=1.0.0; extra == "redis"
Provides-Extra: sql
Requires-Dist: SQLAlchemy>=2.0.0; extra == "sql"
Requires-Dist: asyncpg>=0.27.0; extra == "sql"
Provides-Extra: rmq
Requires-Dist: rstream>=0.40.0; extra == "rmq"
Requires-Dist: msgpack>=1.0.0; extra == "rmq"
Provides-Extra: kafka
Requires-Dist: confluent-kafka>=2.0.0; extra == "kafka"
Requires-Dist: msgpack>=1.0.0; extra == "kafka"
Provides-Extra: dev
Requires-Dist: pytest; extra == "dev"
Requires-Dist: pytest-asyncio; extra == "dev"
Provides-Extra: all
Requires-Dist: redis[hiredis]>=4.0.0; extra == "all"
Requires-Dist: SQLAlchemy>=2.0.0; extra == "all"
Requires-Dist: asyncpg>=0.27.0; extra == "all"
Requires-Dist: msgpack>=1.0.0; extra == "all"
Requires-Dist: rstream>=0.40.0; extra == "all"
Requires-Dist: confluent-kafka>=2.0.0; extra == "all"
Dynamic: license-file
